MANIFEST.in
README.rst
setup.py
chiki/__init__.py
chiki/_flask.py
chiki/app.py
chiki/base.py
chiki/cli.py
chiki/condoms.py
chiki/iptools.py
chiki/jinja.py
chiki/logger.py
chiki/media.py
chiki/settings.py
chiki/sqla.py
chiki/uploads.py
chiki/utils.py
chiki/verify.py
chiki.egg-info/PKG-INFO
chiki.egg-info/SOURCES.txt
chiki.egg-info/dependency_links.txt
chiki.egg-info/entry_points.txt
chiki.egg-info/not-zip-safe
chiki.egg-info/pbr.json
chiki.egg-info/requires.txt
chiki.egg-info/top_level.txt
chiki/admin/__init__.py
chiki/admin/convert.py
chiki/admin/filters.py
chiki/admin/formatters.py
chiki/admin/static.py
chiki/admin/views.py
chiki/api/__init__.py
chiki/api/const.py
chiki/contrib/__init__.py
chiki/contrib/common/__init__.py
chiki/contrib/common/admin.py
chiki/contrib/common/apis.py
chiki/contrib/common/models.py
chiki/contrib/users/__init__.py
chiki/contrib/users/admin.py
chiki/contrib/users/apis.py
chiki/contrib/users/base.py
chiki/contrib/users/forms.py
chiki/contrib/users/funcs.py
chiki/contrib/users/models.py
chiki/contrib/users/views.py
chiki/contrib/users/oauth/__init__.py
chiki/contrib/users/oauth/wechat.py
chiki/data/fonts/1.ttf
chiki/data/fonts/2.ttf
chiki/data/fonts/3.ttf
chiki/data/fonts/4.ttf
chiki/forms/__init__.py
chiki/forms/fields.py
chiki/forms/forms.py
chiki/forms/validators.py
chiki/forms/widgets.py
chiki/mongoengine/__init__.py
chiki/mongoengine/fields.py
chiki/mongoengine/generators.py
chiki/mongoengine/pagination.py
chiki/mongoengine/storages.py
chiki/oauth/__init__.py
chiki/oauth/jssdk.py
chiki/oauth/robot.py
chiki/oauth/wxauth.py
chiki/oauth/wxpay.py
chiki/sms/CCPRestSDK.py
chiki/sms/__init__.py
chiki/sms/send.py
chiki/sms/xmltojson.py
chiki/static/admin/css/bootstrap2/admin.css
chiki/static/admin/css/bootstrap2/rediscli.css
chiki/static/admin/css/bootstrap3/admin.css
chiki/static/admin/css/bootstrap3/rediscli.css
chiki/static/admin/js/actions.js
chiki/static/admin/js/bs2_modal.js
chiki/static/admin/js/bs3_modal.js
chiki/static/admin/js/details_filter.js
chiki/static/admin/js/filters.js
chiki/static/admin/js/form.js
chiki/static/admin/js/rediscli.js
chiki/static/bootstrap/bootstrap2/css/bootstrap-responsive.css
