Metadata-Version: 1.0
Name: chiki
Version: 1.1.0
Summary: Common libs of flask web develop
Home-page: http://www.chiki.org/
Author: Linshao
Author-email: 438985635@qq.com
License: UNKNOWN
Platform: any
